django_production/__init__.py
django_production/__main__.py
django_production/settings.py
django_production-0.1.0.dist-info/entry_points.txt
django_production-0.1.0.dist-info/LICENSE
django_production-0.1.0.dist-info/WHEEL
django_production-0.1.0.dist-info/METADATA
django_production-0.1.0.dist-info/RECORD
