Metadata-Version: 2.1
Name: django-production
Version: 0.1.0
Summary: django-production gets your project production ready
Keywords: django,production,deployment
Author-email: Peter Baumgartner <pete@lincolnloop.com>
Classifier: Development Status :: 4 - Beta
Classifier: Intended Audience :: Developers
Classifier: License :: OSI Approved :: MIT License
Classifier: Programming Language :: Python :: 3
Classifier: Framework :: Django
Requires-Dist: django-environ
Requires-Dist: whitenoise
Requires-Dist: django-webserver[gunicorn]
Requires-Dist: django-alive
Requires-Dist: pytest ; extra == "test"
Requires-Dist: pytest-cov ; extra == "test"
Project-URL: Home, https://github.com/lincolnloop/django-production
Project-URL: Issues, https://github.com/lincolnloop/django-production/issues
Provides-Extra: test
